aistrainer/aistrainer.py
aistrainer/models.py
aistrainer-0.0.13.dist-info/LICENSE
aistrainer-0.0.13.dist-info/METADATA
aistrainer-0.0.13.dist-info/WHEEL
aistrainer-0.0.13.dist-info/top_level.txt
aistrainer-0.0.13.dist-info/RECORD
