Metadata-Version: 2.1
Name: aistrainer
Version: 0.0.13
Summary: AI Specialization Trainer for LLM models
Author-email: Vladimir Petrukhin <man4j@ya.ru>
Project-URL: Homepage, https://github.com/Equiron-AI/aistrainer
Classifier: Development Status :: 4 - Beta
Classifier: Programming Language :: Python :: 3.10
Classifier: Programming Language :: Python :: 3.11
Classifier: License :: OSI Approved :: MIT License
Classifier: Operating System :: OS Independent
Requires-Python: >=3.10
License-File: LICENSE
Requires-Dist: transformers >=4.44.2
Requires-Dist: datasets >=2.21.0
Requires-Dist: peft >=0.12.0
Requires-Dist: deepspeed ==0.15.1
Requires-Dist: sentencepiece >=0.2.0
